qitian_django_starting-0.0.1.dist-info/METADATA
qitian_django_starting-0.0.1.dist-info/RECORD
qitian_django_starting-0.0.1.dist-info/WHEEL
qitian_django_starting-0.0.1.dist-info/top_level.txt
system/__init__.py
system/admin.py
system/apps.py
system/context_processors.py
system/middleware.py
system/models.py
system/views.py
system/middleware/__init__.py
system/middleware/site.py
system/migrations/0001_initial.py
system/migrations/__init__.py
system/templatetags/__init__.py
system/templatetags/dict_utils.py
system/templatetags/random_numbers.py
system/utils/Cipher.py
system/utils/__init__.py
system/utils/convert.py
system/utils/sms.py
system/utils/storage.py
system/utils/tools.py
system/utils/views/__init__.py
system/utils/views/base.py
ueditor/__init__.py
ueditor/controller.py
ueditor/models.py
ueditor/settings.py
ueditor/urls.py
ueditor/widgets.py
usercenter/__init__.py
usercenter/admin.py
usercenter/apps.py
usercenter/models.py
usercenter/tests.py
usercenter/urls.py
usercenter/views.py
usercenter/migrations/0001_initial.py
usercenter/migrations/0002_auto_20180825_2030.py
usercenter/migrations/0003_auto_20180825_2316.py
usercenter/migrations/0004_viplogs_order.py
usercenter/migrations/__init__.py
usercenter/utils/__init__.py
usercenter/utils/auth.py
